{
  "resourceType": "ValueSet",
  "id": "MammoCalcificationTypeVS",
  "url": "http://hl7.org/fhir/us/breast-radiology/ValueSet/MammoCalcificationTypeVS",
  "version": "0.0.2",
  "name": "MammoCalcificationTypeVS",
  "title": "Mammography Calcification Type ValueSet",
  "status": "draft",
  "date": "2019-11-01",
  "publisher": "Hl7-Clinical Interoperability Council",
  "contact": [
    {
      "telecom": [
        {
          "system": "url",
          "value": "http://www.hl7.org/Special/committees/cic"
        }
      ]
    }
  ],
  "description": "Mammography calcification types value set.",
  "compose": {
    "include": [
      {
        "system": "http://hl7.org/fhir/us/breast-radiology/CodeSystem/MammoCalcificationTypeCS",
        "concept": [
          {
            "code": "Amorphous",
            "display": "Amorphous"
          },
          {
            "code": "Coarse",
            "display": "Coarse"
          },
          {
            "code": "Dystrophic",
            "display": "Dystrophic"
          },
          {
            "code": "Eggshell",
            "display": "Eggshell"
          },
          {
            "code": "FineADDPrefix",
            "display": "Fine ADD prefix"
          },
          {
            "code": "GenericCalcification",
            "display": "Generic calcification"
          },
          {
            "code": "HeterogeneousADDPrefixCourse",
            "display": "Heterogeneous ADD prefix course"
          },
          {
            "code": "Indistinct",
            "display": "Indistinct"
          },
          {
            "code": "LargeRodlike",
            "display": "Large rodlike"
          },
          {
            "code": "Layering",
            "display": "Layering"
          },
          {
            "code": "LinearADDPrefixFine",
            "display": "Linear ADD prefix fine"
          },
          {
            "code": "Lucent-centered",
            "display": "Lucent-centered"
          },
          {
            "code": "MilkOfCalcium",
            "display": "Milk of calcium"
          },
          {
            "code": "PleomorphicADDPrefixFine",
            "display": "Pleomorphic ADD prefix fine"
          },
          {
            "code": "Punctate",
            "display": "Punctate"
          },
          {
            "code": "Rim",
            "display": "Rim"
          },
          {
            "code": "Round",
            "display": "Round"
          },
          {
            "code": "Skin",
            "display": "Skin"
          },
          {
            "code": "Spherical",
            "display": "Spherical"
          },
          {
            "code": "Suture",
            "display": "Suture"
          },
          {
            "code": "Vascular",
            "display": "Vascular"
          }
        ]
      }
    ]
  }
}