<?xml version="1.0" encoding="UTF-8"?><ImplementationGuide xmlns="http://hl7.org/fhir"><id value="hl7.fhir.us.breast-radiology"/><text><status value="generated"/><div xmlns="http://www.w3.org/1999/xhtml"><h2>Breast_Radiology_Reporting_1st_STU_ballot</h2><p>The official URL for this implementation guide is: </p><pre>http://hl7.org/fhir/us/breast-radiology/ImplementationGuide/hl7.fhir.us.breast-radiology</pre><div><p>Breast Radiology Reporting Implementation Guide</p>
</div></div></text><url value="http://hl7.org/fhir/us/breast-radiology/ImplementationGuide/hl7.fhir.us.breast-radiology"/><version value="0.0.2"/><name value="Breast_Radiology_Reporting_1st_STU_ballot"/><title value="Breast Radiology Reporting - 1st STU ballot"/><status value="draft"/><experimental value="false"/><date value="2020-02-06T19:42:35-06:00"/><publisher value="Hl7 - Clinical Interoperability Council"/><contact><telecom><system value="other"/><value value="http://hl7.org/Special/committees/cic"/></telecom></contact><description value="Breast Radiology Reporting Implementation Guide"/><jurisdiction><coding><system value="http://unstats.un.org/unsd/methods/m49/m49.htm"/><code value="001"/></coding></jurisdiction><packageId value="hl7.fhir.us.breast-radiology"/><license value="CC0-1.0"/><fhirVersion value="4.0.1"/><definition><grouping id="BaseResources"><name value="Main Resources"/><description value="This section contains the main top level resources that are used in a Breast Radiology Report."/></grouping><grouping id="CommonResources"><name value="Common Resources"/><description value="This section contains resources that are commonly used throughout a Breast Radiology Report"/></grouping><grouping id="CommonCodesVS"><name value="Common ValueSets "/><description value="This section contains value sets that are commonly used throughout a Breast Radiology Report"/></grouping><grouping id="CommonCodesCS"><name value="Common CodeSystems"/><description value="This section contains code systems that are commonly used throughout a Breast Radiology Report"/></grouping><grouping id="MGResources"><name value="Mammography Resources"/><description value="This section contains resources used specifically in a Mammography exam"/></grouping><grouping id="MGCodesVS"><name value="Mammography ValueSets"/><description value="This section contains value sets used specifically in a Mammography exam"/></grouping><grouping id="MGCodesCS"><name value="Mammography CodeSystems"/><description value="This section contains code systems used specifically in a Mammography exam"/></grouping><grouping id="MRIResources"><name value="MRI Resources"/><description value="This section contains resources used specifically in a MRI exam"/></grouping><grouping id="MRICodesVS"><name value="MRI ValueSets"/><description value="This section contains value sets used specifically in a MRI exam"/></grouping><grouping id="MRICodesCS"><name value="MRI CodeSystems"/><description value="This section contains code systems used specifically in a MRI exam"/></grouping><grouping id="USResources"><name value="Ultra-Sound Resources"/><description value="This section contains resources used specifically in a Ultra-Sound exam"/></grouping><grouping id="USCodesVS"><name value="Ultra-Sound ValueSets"/><description value="This section contains value sets used specifically in a Ultra-Sound exam"/></grouping><grouping id="USCodesCS"><name value="Ultra-Sound CodeSystems"/><description value="This section contains code systems used specifically in a Ultra-Sound exam"/></grouping><grouping id="NMResources"><name value="Nuclear Medicine Resources"/><description value="This section contains resources used specifically in a Nuclear Medicine exam"/></grouping><grouping id="NMCodesVS"><name value="Nuclear Medicine ValueSets"/><description value="This section contains value sets used specifically in a Nuclear Medicine exam"/></grouping><grouping id="NMCodesCS"><name value="Nuclear Medicine CodeSystems"/><description value="This section contains code systems used specifically in a Nuclear Medicine exam"/></grouping><grouping id="AimResources"><name value="AIM Resources"/><description value="This section contains resources used specifically by AIM"/></grouping><grouping id="AimCodesVS"><name value="AIM ValueSets"/><description value="This section contains value sets used specifically by AIM"/></grouping><grouping id="AimCodesCS"><name value="AIM CodeSystems"/><description value="This section contains code systems used specifically by AIM"/></grouping><grouping id="Fragments"><name value="Fragments"/><description value="This section the fragments that are used to define the resources"/></grouping><grouping id="ExtensionResources"><name value="Extension"/><description value="Extension Resource Definitions"/></grouping><grouping xmlns="http://hl7.org/fhir" id="_dyn_capabilitystatement">
  <name value="Behavior: Capability Statements"/>
  <description value="The following artifacts define the specific capabilities that different types of systems are expected to have in order to comply with this implementation guide.  Systems complying with the implementation guide are expected to declare conformance to one or more of the following capability statements."/>
</grouping>
<grouping xmlns="http://hl7.org/fhir" id="_dyn_operationdefinition">
  <name value="Behavior: Operation Definitions"/>
  <description value="These are custom operations that can be supported by and/or invoked by systems complying with this implementation guide"/>
</grouping>
<grouping xmlns="http://hl7.org/fhir" id="_dyn_messagedefinition">
  <name value="Behavior: Message Definitions"/>
  <description value="These define the types of messages that can be sent and/or received by systems complying with this implementation guide"/>
</grouping>
<grouping xmlns="http://hl7.org/fhir" id="_str_graphdefinition">
  <name value="Structures: Graph Definitions"/>
  <description value="These define collections of interrelated resources that are useful to pass around as a group"/>
</grouping>
<grouping xmlns="http://hl7.org/fhir" id="_str_logicalmodel">
  <name value="Structures: Logical Models"/>
  <description value="These define data models that represent the domain covered by this implementation guide in more business-friendly terms than the underlying FHIR resources."/>
</grouping>
<grouping xmlns="http://hl7.org/fhir" id="_str_questionnaire">
  <name value="Structures: Questionnaires"/>
  <description value="These define forms used by systems conforming with this implementation guide to capture or expose data to end users"/>
</grouping>
<grouping xmlns="http://hl7.org/fhir" id="_str_abstractprofile">
  <name value="Structures: Abstract Profiles"/>
  <description value="These are profiles on resources or data types that describe patterns used by other profiles, but can't be instantiated directly.  I.e. instances can conform to profiles *based* on these abstract profiles, but don't declare conformance to the abstract profiles themselves."/>
</grouping>
<grouping xmlns="http://hl7.org/fhir" id="_str_profile">
  <name value="Structures: Resource Profiles"/>
  <description value="These define constraints on FHIR resources that need to be complied with by conformant implementations"/>
</grouping>
<grouping xmlns="http://hl7.org/fhir" id="_str_datatype">
  <name value="Structures: Data Type Profiles"/>
  <description value="These define constraints on FHIR data types that need to be complied with by conformant implementations"/>
</grouping>
<grouping xmlns="http://hl7.org/fhir" id="_str_extension">
  <name value="Structures: Extension Definitions"/>
  <description value="These define constraints on FHIR data types that need to be complied with by conformant implementations"/>
</grouping>
<grouping xmlns="http://hl7.org/fhir" id="_term_valueset">
  <name value="Terminology: Value Sets"/>
  <description value="These define sets of codes used by systems conforming with this implementation guide"/>
</grouping>
<grouping xmlns="http://hl7.org/fhir" id="_term_codesystem">
  <name value="Terminology: Code Systems"/>
  <description value="These define new code systems used by systems conforming with this implementation guide"/>
</grouping>
<grouping xmlns="http://hl7.org/fhir" id="_term_namingsystem">
  <name value="Terminology: Naming Systems"/>
  <description value="These define identifier and/or code system identities used by systems conforming with this implementation guide"/>
</grouping>
<grouping xmlns="http://hl7.org/fhir" id="_map_structuremap">
  <name value="Terminology: Structure Maps"/>
  <description value="These define transformations to convert between data structures used by systems conforming with this implementation guide"/>
</grouping>
<grouping xmlns="http://hl7.org/fhir" id="_map_conceptmap">
  <name value="Terminology: Concept Maps"/>
  <description value="These define transformations to convert between codes by systems conforming with this implementation guide"/>
</grouping>
<grouping xmlns="http://hl7.org/fhir" id="_ex_examplescenario">
  <name value="Example: Example Scenarios"/>
  <description value="These define groups of interrelated examples that demonstrate one or more of the workflows supported by this implementation guide"/>
</grouping>
<grouping xmlns="http://hl7.org/fhir" id="_ex_example">
  <name value="Example: Example Instances"/>
  <description value="These are example instances that show what data produced and consumed by systems conforming with this implementation guide might look like"/>
</grouping>
<grouping xmlns="http://hl7.org/fhir" id="_other">
  <name value="Other"/>
  <description value="These are resources that are used within this implementation guide that don't fit into one of the other categories"/>
</grouping>
<resource><extension url="http://hl7.org/fhir/tools/StructureDefinition/resource-information"><valueString value="CodeSystem"/></extension><extension url="http://hl7.org/fhir/StructureDefinition/implementationguide-page"><valueUri value="CodeSystem-AbnormalityCystTypeCS.html"/></extension><reference><reference value="CodeSystem/AbnormalityCystTypeCS"/></reference><name value="Cyst Type CodeSystem"/><description value="Cyst abnormality type CodeSystem."/><exampleBoolean value="false"/><groupingId value="CommonCodesCS"/></resource><resource><extension url="http://hl7.org/fhir/tools/StructureDefinition/resource-information"><valueString value="CodeSystem"/></extension><extension url="http://hl7.org/fhir/StructureDefinition/implementationguide-page"><valueUri value="CodeSystem-AbnormalityDuctTypeCS.html"/></extension><reference><reference value="CodeSystem/AbnormalityDuctTypeCS"/></reference><name value="Duct Type CodeSystem"/><description value="Duct abnormality types code system."/><exampleBoolean value="false"/><groupingId value="CommonCodesCS"/></resource><resource><extension url="http://hl7.org/fhir/tools/StructureDefinition/resource-information"><valueString value="CodeSystem"/></extension><extension url="http://hl7.org/fhir/StructureDefinition/implementationguide-page"><valueUri value="CodeSystem-AbnormalityLymphNodeTypeCS.html"/></extension><reference><reference value="CodeSystem/AbnormalityLymphNodeTypeCS"/></reference><name value="Lymph Node Type CodeSystem"/><description value="Lymph node abnormality types code system."/><exampleBoolean value="false"/><groupingId value="CommonCodesCS"/></resource><resource><extension url="http://hl7.org/fhir/tools/StructureDefinition/resource-information"><valueString value="CodeSystem"/></extension><extension url="http://hl7.org/fhir/StructureDefinition/implementationguide-page"><valueUri value="CodeSystem-BiRadsAssessmentCategoriesCS.html"/></extension><reference><reference value="CodeSystem/BiRadsAssessmentCategoriesCS"/></reference><name value="BiRads(r) Assessment Category Codes CodeSystem"/><description value="BiRads(r) Assessment Category code system."/><exampleBoolean value="false"/><groupingId value="CommonCodesCS"/></resource><resource><extension url="http://hl7.org/fhir/tools/StructureDefinition/resource-information"><valueString value="CodeSystem"/></extension><extension url="http://hl7.org/fhir/StructureDefinition/implementationguide-page"><valueUri value="CodeSystem-BreastLocationClockCS.html"/></extension><reference><reference value="CodeSystem/BreastLocationClockCS"/></reference><name value="Breast Location Clock CodeSystem"/><description value="Breast body location angles (expressed in clock-face units) code system."/><exampleBoolean value="false"/><groupingId value="CommonCodesCS"/></resource><resource><extension url="http://hl7.org/fhir/tools/StructureDefinition/resource-information"><valueString value="CodeSystem"/></extension><extension url="http://hl7.org/fhir/StructureDefinition/implementationguide-page"><valueUri value="CodeSystem-BreastLocationDepthCS.html"/></extension><reference><reference value="CodeSystem/BreastLocationDepthCS"/></reference><name value="Breast Location Depth CodeSystem"/><description value="Breast body location depth code system."/><exampleBoolean value="false"/><groupingId value="CommonCodesCS"/></resource><resource><extension url="http://hl7.org/fhir/tools/StructureDefinition/resource-information"><valueString value="CodeSystem"/></extension><extension url="http://hl7.org/fhir/StructureDefinition/implementationguide-page"><valueUri value="CodeSystem-BreastLocationQuadrantCS.html"/></extension><reference><reference value="CodeSystem/BreastLocationQuadrantCS"/></reference><name value="Breast Location Quadrant CodeSystem"/><description value="Breast body location quadrant code system."/><exampleBoolean value="false"/><groupingId value="CommonCodesCS"/></resource><resource><extension url="http://hl7.org/fhir/tools/StructureDefinition/resource-information"><valueString value="CodeSystem"/></extension><extension url="http://hl7.org/fhir/StructureDefinition/implementationguide-page"><valueUri value="CodeSystem-BreastLocationRegionCS.html"/></extension><reference><reference value="CodeSystem/BreastLocationRegionCS"/></reference><name value="Breast Location Region CodeSystem"/><description value="Breast body location region code system."/><exampleBoolean value="false"/><groupingId value="CommonCodesCS"/></resource><resource><extension url="http://hl7.org/fhir/tools/StructureDefinition/resource-information"><valueString value="CodeSystem"/></extension><extension url="http://hl7.org/fhir/StructureDefinition/implementationguide-page"><valueUri value="CodeSystem-CalcificationDistributionCS.html"/></extension><reference><reference value="CodeSystem/CalcificationDistributionCS"/></reference><name value="Calcification Distribution CodeSystem"/><description value="Calcification Distribution in an abnormality code system."/><exampleBoolean value="false"/><groupingId value="CommonCodesCS"/></resource><resource><extension url="http://hl7.org/fhir/tools/StructureDefinition/resource-information"><valueString value="CodeSystem"/></extension><extension url="http://hl7.org/fhir/StructureDefinition/implementationguide-page"><valueUri value="CodeSystem-CompositionSectionSliceCodes.html"/></extension><reference><reference value="CodeSystem/CompositionSectionSliceCodes"/></reference><name value="Composition Section Slice Codes CodeSystem"/><description value="Composition Section Slice Codes code system"/><exampleBoolean value="false"/><groupingId value="CommonCodesCS"/></resource><resource><extension url="http://hl7.org/fhir/tools/StructureDefinition/resource-information"><valueString value="CodeSystem"/></extension><extension url="http://hl7.org/fhir/StructureDefinition/implementationguide-page"><valueUri value="CodeSystem-ConsistentWithCodeSystemCS.html"/></extension><reference><reference value="CodeSystem/ConsistentWithCodeSystemCS"/></reference><name value="Consistent With CodeSystem"/><description value="ConsistentWith code system"/><exampleBoolean value="false"/><groupingId value="CommonCodesCS"/></resource><resource><extension url="http://hl7.org/fhir/tools/StructureDefinition/resource-information"><valueString value="CodeSystem"/></extension><extension url="http://hl7.org/fhir/StructureDefinition/implementationguide-page"><valueUri value="CodeSystem-ConsistentWithQualifierCS.html"/></extension><reference><reference value="CodeSystem/ConsistentWithQualifierCS"/></reference><name value="ConsistentWith Qualifier CodeSystem"/><description value="ConsistentWithQualifier  code system"/><exampleBoolean value="false"/><groupingId value="CommonCodesCS"/></resource><resource><extension url="http://hl7.org/fhir/tools/StructureDefinition/resource-information"><valueString value="CodeSystem"/></extension><extension url="http://hl7.org/fhir/StructureDefinition/implementationguide-page"><valueUri value="CodeSystem-CorrespondsWithCodeSystemCS.html"/></extension><reference><reference value="CodeSystem/CorrespondsWithCodeSystemCS"/></reference><name value="Consistent With CodeSystem"/><description value="CorrespondsWith code system"/><exampleBoolean value="false"/><groupingId value="CommonCodesCS"/></resource><resource><extension url="http://hl7.org/fhir/tools/StructureDefinition/resource-information"><valueString value="CodeSystem"/></extension><extension url="http://hl7.org/fhir/StructureDefinition/implementationguide-page"><valueUri value="CodeSystem-FibroadenomaCodeSystemCS.html"/></extension><reference><reference value="CodeSystem/FibroadenomaCodeSystemCS"/></reference><name value="Fibroadenoma CodeSystem"/><description value="Fibroadenoma values code system."/><exampleBoolean value="false"/><groupingId value="CommonCodesCS"/></resource><resource><extension url="http://hl7.org/fhir/tools/StructureDefinition/resource-information"><valueString value="CodeSystem"/></extension><extension url="http://hl7.org/fhir/StructureDefinition/implementationguide-page"><valueUri value="CodeSystem-ForeignObjectCS.html"/></extension><reference><reference value="CodeSystem/ForeignObjectCS"/></reference><name value="Foreign Object CodeSystem"/><description value="Foreign objects observed during a Breast Radiology exam code system."/><exampleBoolean value="false"/><groupingId value="CommonCodesCS"/></resource><resource><extension url="http://hl7.org/fhir/tools/StructureDefinition/resource-information"><valueString value="CodeSystem"/></extension><extension url="http://hl7.org/fhir/StructureDefinition/implementationguide-page"><valueUri value="CodeSystem-MammoCalcificationTypeCS.html"/></extension><reference><reference value="CodeSystem/MammoCalcificationTypeCS"/></reference><name value="Mammography Calcification Type CodeSystem"/><description value="Mammography calcification type code system."/><exampleBoolean value="false"/><groupingId value="MGCodesCS"/></resource><resource><extension url="http://hl7.org/fhir/tools/StructureDefinition/resource-information"><valueString value="CodeSystem"/></extension><extension url="http://hl7.org/fhir/StructureDefinition/implementationguide-page"><valueUri value="CodeSystem-MarginCS.html"/></extension><reference><reference value="CodeSystem/MarginCS"/></reference><name value="MarginCodeSystem"/><description value="Margin code system."/><exampleBoolean value="false"/><groupingId value="CommonCodesCS"/></resource><resource><extension url="http://hl7.org/fhir/tools/StructureDefinition/resource-information"><valueString value="CodeSystem"/></extension><extension url="http://hl7.org/fhir/StructureDefinition/implementationguide-page"><valueUri value="CodeSystem-MassTypeCS.html"/></extension><reference><reference value="CodeSystem/MassTypeCS"/></reference><name value="Mass Type CodeSystem"/><description value="Codes defining mass refinements."/><exampleBoolean value="false"/><groupingId value="CommonCodesCS"/></resource><resource><extension url="http://hl7.org/fhir/tools/StructureDefinition/resource-information"><valueString value="CodeSystem"/></extension><extension url="http://hl7.org/fhir/StructureDefinition/implementationguide-page"><valueUri value="CodeSystem-MGAbnormalityAsymmetryTypeCS.html"/></extension><reference><reference value="CodeSystem/MGAbnormalityAsymmetryTypeCS"/></reference><name value="Mammography Asymmetry Type CodeSystem"/><description value="Mammography asymmetry abnormality type code system."/><exampleBoolean value="false"/><groupingId value="MGCodesCS"/></resource><resource><extension url="http://hl7.org/fhir/tools/StructureDefinition/resource-information"><valueString value="CodeSystem"/></extension><extension url="http://hl7.org/fhir/StructureDefinition/implementationguide-page"><valueUri value="CodeSystem-MGAbnormalityDensityTypeCS.html"/></extension><reference><reference value="CodeSystem/MGAbnormalityDensityTypeCS"/></reference><name value="Mammography Density Type CodeSystem"/><description value="Mammography density abnormality refinement types code system."/><exampleBoolean value="false"/><groupingId value="MGCodesCS"/></resource><resource><extension url="http://hl7.org/fhir/tools/StructureDefinition/resource-information"><valueString value="CodeSystem"/></extension><extension url="http://hl7.org/fhir/StructureDefinition/implementationguide-page"><valueUri value="CodeSystem-MGBreastDensityCS.html"/></extension><reference><reference value="CodeSystem/MGBreastDensityCS"/></reference><name value="Mammography Breast Density CodeSystem"/><description value="Mammography breast density values code system."/><exampleBoolean value="false"/><groupingId value="MGCodesCS"/></resource><resource><extension url="http://hl7.org/fhir/tools/StructureDefinition/resource-information"><valueString value="CodeSystem"/></extension><extension url="http://hl7.org/fhir/StructureDefinition/implementationguide-page"><valueUri value="CodeSystem-MGDensityCS.html"/></extension><reference><reference value="CodeSystem/MGDensityCS"/></reference><name value="Mammography Density CodeSystem"/><description value="Mammography density code system."/><exampleBoolean value="false"/><groupingId value="MGCodesCS"/></resource><resource><extension url="http://hl7.org/fhir/tools/StructureDefinition/resource-information"><valueString value="CodeSystem"/></extension><extension url="http://hl7.org/fhir/StructureDefinition/implementationguide-page"><valueUri value="CodeSystem-NotPreviouslySeenCodeSystemCS.html"/></extension><reference><reference value="CodeSystem/NotPreviouslySeenCodeSystemCS"/></reference><name value="Not Previously Seen CodeSystem"/><description value="NotPreviouslySeen code system"/><exampleBoolean value="false"/><groupingId value="CommonCodesCS"/></resource><resource><extension url="http://hl7.org/fhir/tools/StructureDefinition/resource-information"><valueString value="CodeSystem"/></extension><extension url="http://hl7.org/fhir/StructureDefinition/implementationguide-page"><valueUri value="CodeSystem-ObservationCodes.html"/></extension><reference><reference value="CodeSystem/ObservationCodes"/></reference><name value="Observation Codes CodeSystem"/><description value="Observation Codes code system"/><exampleBoolean value="false"/><groupingId value="CommonCodesCS"/></resource><resource><extension url="http://hl7.org/fhir/tools/StructureDefinition/resource-information"><valueString value="CodeSystem"/></extension><extension url="http://hl7.org/fhir/StructureDefinition/implementationguide-page"><valueUri value="CodeSystem-ObservationComponentSliceCodes.html"/></extension><reference><reference value="CodeSystem/ObservationComponentSliceCodes"/></reference><name value="Component Slice Codes CodeSystem"/><description value="Component Slice Codes code system"/><exampleBoolean value="false"/><groupingId value="CommonCodesCS"/></resource><resource><extension url="http://hl7.org/fhir/tools/StructureDefinition/resource-information"><valueString value="CodeSystem"/></extension><extension url="http://hl7.org/fhir/StructureDefinition/implementationguide-page"><valueUri value="CodeSystem-ObservedChangesCS.html"/></extension><reference><reference value="CodeSystem/ObservedChangesCS"/></reference><name value="Observed Changes CodeSystem"/><description value="Observed changes in an abnormality code system."/><exampleBoolean value="false"/><groupingId value="CommonCodesCS"/></resource><resource><extension url="http://hl7.org/fhir/tools/StructureDefinition/resource-information"><valueString value="CodeSystem"/></extension><extension url="http://hl7.org/fhir/StructureDefinition/implementationguide-page"><valueUri value="CodeSystem-ObservedFeatureCS.html"/></extension><reference><reference value="CodeSystem/ObservedFeatureCS"/></reference><name value="Observed Feature CodeSystem"/><description value="Observed Feature seen during a breast examination."/><exampleBoolean value="false"/><groupingId value="CommonCodesCS"/></resource><resource><extension url="http://hl7.org/fhir/tools/StructureDefinition/resource-information"><valueString value="CodeSystem"/></extension><extension url="http://hl7.org/fhir/StructureDefinition/implementationguide-page"><valueUri value="CodeSystem-OrientationCS.html"/></extension><reference><reference value="CodeSystem/OrientationCS"/></reference><name value="Orientation CodeSystem"/><description value="Orientation CodeSystem"/><exampleBoolean value="false"/><groupingId value="CommonCodesCS"/></resource><resource><extension url="http://hl7.org/fhir/tools/StructureDefinition/resource-information"><valueString value="CodeSystem"/></extension><extension url="http://hl7.org/fhir/StructureDefinition/implementationguide-page"><valueUri value="CodeSystem-RecommendationsCodeSystemCS.html"/></extension><reference><reference value="CodeSystem/RecommendationsCodeSystemCS"/></reference><name value="Recommendations CodeSystem"/><description value="Recommendations code system"/><exampleBoolean value="false"/><groupingId value="CommonCodesCS"/></resource><resource><extension url="http://hl7.org/fhir/tools/StructureDefinition/resource-information"><valueString value="CodeSystem"/></extension><extension url="http://hl7.org/fhir/StructureDefinition/implementationguide-page"><valueUri value="CodeSystem-ShapeCS.html"/></extension><reference><reference value="CodeSystem/ShapeCS"/></reference><name value="Shape CodeSystem"/><description value="Shape values code system."/><exampleBoolean value="false"/><groupingId value="CommonCodesCS"/></resource><resource><extension url="http://hl7.org/fhir/tools/StructureDefinition/resource-information"><valueString value="ValueSet"/></extension><extension url="http://hl7.org/fhir/StructureDefinition/implementationguide-page"><valueUri value="ValueSet-AbnormalityCystTypeVS.html"/></extension><reference><reference value="ValueSet/AbnormalityCystTypeVS"/></reference><name value="Cyst Abnormalities ValueSet"/><description value="Cyst abnormality types value set."/><exampleBoolean value="false"/><groupingId value="CommonCodesVS"/></resource><resource><extension url="http://hl7.org/fhir/tools/StructureDefinition/resource-information"><valueString value="ValueSet"/></extension><extension url="http://hl7.org/fhir/StructureDefinition/implementationguide-page"><valueUri value="ValueSet-AbnormalityDuctTypeVS.html"/></extension><reference><reference value="ValueSet/AbnormalityDuctTypeVS"/></reference><name value="Duct ValueSet"/><description value="Duct node abnormality types value set."/><exampleBoolean value="false"/><groupingId value="CommonCodesVS"/></resource><resource><extension url="http://hl7.org/fhir/tools/StructureDefinition/resource-information"><valueString value="ValueSet"/></extension><extension url="http://hl7.org/fhir/StructureDefinition/implementationguide-page"><valueUri value="ValueSet-AbnormalityLymphNodeTypeVS.html"/></extension><reference><reference value="ValueSet/AbnormalityLymphNodeTypeVS"/></reference><name value="Lymph Node ValueSet"/><description value="lymph node abnormality types value set."/><exampleBoolean value="false"/><groupingId value="CommonCodesVS"/></resource><resource><extension url="http://hl7.org/fhir/tools/StructureDefinition/resource-information"><valueString value="ValueSet"/></extension><extension url="http://hl7.org/fhir/StructureDefinition/implementationguide-page"><valueUri value="ValueSet-BiRadsAssessmentCategoriesVS.html"/></extension><reference><reference value="ValueSet/BiRadsAssessmentCategoriesVS"/></reference><name value="BiRads(r) Assessment Category ValueSet"/><description value="BiRads(r) Assessment Category value set."/><exampleBoolean value="false"/><groupingId value="CommonCodesVS"/></resource><resource><extension url="http://hl7.org/fhir/tools/StructureDefinition/resource-information"><valueString value="ValueSet"/></extension><extension url="http://hl7.org/fhir/StructureDefinition/implementationguide-page"><valueUri value="ValueSet-BreastLocationClockVS.html"/></extension><reference><reference value="ValueSet/BreastLocationClockVS"/></reference><name value="Breast Location Clock ValueSet"/><description value="Breast body location angles (expressed in clock-face units) value set."/><exampleBoolean value="false"/><groupingId value="CommonCodesVS"/></resource><resource><extension url="http://hl7.org/fhir/tools/StructureDefinition/resource-information"><valueString value="ValueSet"/></extension><extension url="http://hl7.org/fhir/StructureDefinition/implementationguide-page"><valueUri value="ValueSet-BreastLocationDepthVS.html"/></extension><reference><reference value="ValueSet/BreastLocationDepthVS"/></reference><name value="Breast Location Depth ValueSet"/><description value="Breast body location depth value set."/><exampleBoolean value="false"/><groupingId value="CommonCodesVS"/></resource><resource><extension url="http://hl7.org/fhir/tools/StructureDefinition/resource-information"><valueString value="ValueSet"/></extension><extension url="http://hl7.org/fhir/StructureDefinition/implementationguide-page"><valueUri value="ValueSet-BreastLocationQuadrantVS.html"/></extension><reference><reference value="ValueSet/BreastLocationQuadrantVS"/></reference><name value="Breast Location Quadrant ValueSet"/><description value="Breast body location quadrant code system value set."/><exampleBoolean value="false"/><groupingId value="CommonCodesVS"/></resource><resource><extension url="http://hl7.org/fhir/tools/StructureDefinition/resource-information"><valueString value="ValueSet"/></extension><extension url="http://hl7.org/fhir/StructureDefinition/implementationguide-page"><valueUri value="ValueSet-BreastLocationRegionVS.html"/></extension><reference><reference value="ValueSet/BreastLocationRegionVS"/></reference><name value="Breast Location Region ValueSet"/><description value="Breast body location region value set."/><exampleBoolean value="false"/><groupingId value="CommonCodesVS"/></resource><resource><extension url="http://hl7.org/fhir/tools/StructureDefinition/resource-information"><valueString value="ValueSet"/></extension><extension url="http://hl7.org/fhir/StructureDefinition/implementationguide-page"><valueUri value="ValueSet-CalcificationDistributionVS.html"/></extension><reference><reference value="ValueSet/CalcificationDistributionVS"/></reference><name value="Calcification Distribution ValueSet"/><description value="Calcification Distribution of an abnormality value set."/><exampleBoolean value="false"/><groupingId value="CommonCodesVS"/></resource><resource><extension url="http://hl7.org/fhir/tools/StructureDefinition/resource-information"><valueString value="ValueSet"/></extension><extension url="http://hl7.org/fhir/StructureDefinition/implementationguide-page"><valueUri value="ValueSet-ConsistentWithQualifierVS.html"/></extension><reference><reference value="ValueSet/ConsistentWithQualifierVS"/></reference><name value="ConsistentWithQualifier ValueSet"/><description value="ConsistentWithQualifier value set."/><exampleBoolean value="false"/><groupingId value="CommonCodesVS"/></resource><resource><extension url="http://hl7.org/fhir/tools/StructureDefinition/resource-information"><valueString value="ValueSet"/></extension><extension url="http://hl7.org/fhir/StructureDefinition/implementationguide-page"><valueUri value="ValueSet-ConsistentWithVS.html"/></extension><reference><reference value="ValueSet/ConsistentWithVS"/></reference><name value="ConsistentWith ValueSet"/><description value="ConsistentWith value set."/><exampleBoolean value="false"/><groupingId value="CommonCodesVS"/></resource><resource><extension url="http://hl7.org/fhir/tools/StructureDefinition/resource-information"><valueString value="ValueSet"/></extension><extension url="http://hl7.org/fhir/StructureDefinition/implementationguide-page"><valueUri value="ValueSet-CorrespondsWithVS.html"/></extension><reference><reference value="ValueSet/CorrespondsWithVS"/></reference><name value="CorrespondsWith ValueSet"/><description value="CorrespondsWith value set."/><exampleBoolean value="false"/><groupingId value="CommonCodesVS"/></resource><resource><extension url="http://hl7.org/fhir/tools/StructureDefinition/resource-information"><valueString value="ValueSet"/></extension><extension url="http://hl7.org/fhir/StructureDefinition/implementationguide-page"><valueUri value="ValueSet-FibroadenomaVS.html"/></extension><reference><reference value="ValueSet/FibroadenomaVS"/></reference><name value="Fibroadenoma ValueSet"/><description value="Fibroadenoma value set."/><exampleBoolean value="false"/><groupingId value="CommonCodesVS"/></resource><resource><extension url="http://hl7.org/fhir/tools/StructureDefinition/resource-information"><valueString value="ValueSet"/></extension><extension url="http://hl7.org/fhir/StructureDefinition/implementationguide-page"><valueUri value="ValueSet-ForeignObjectVS.html"/></extension><reference><reference value="ValueSet/ForeignObjectVS"/></reference><name value="Foreign Object ValueSet"/><description value="Foreign objects observed during a Breast Radiology exam value set"/><exampleBoolean value="false"/><groupingId value="CommonCodesVS"/></resource><resource><extension url="http://hl7.org/fhir/tools/StructureDefinition/resource-information"><valueString value="ValueSet"/></extension><extension url="http://hl7.org/fhir/StructureDefinition/implementationguide-page"><valueUri value="ValueSet-MammoCalcificationTypeVS.html"/></extension><reference><reference value="ValueSet/MammoCalcificationTypeVS"/></reference><name value="Mammography Calcification Type ValueSet"/><description value="Mammography calcification types value set."/><exampleBoolean value="false"/><groupingId value="MGCodesVS"/></resource><resource><extension url="http://hl7.org/fhir/tools/StructureDefinition/resource-information"><valueString value="ValueSet"/></extension><extension url="http://hl7.org/fhir/StructureDefinition/implementationguide-page"><valueUri value="ValueSet-MarginVS.html"/></extension><reference><reference value="ValueSet/MarginVS"/></reference><name value="Margin ValueSet"/><description value="Margin ValueSet."/><exampleBoolean value="false"/><groupingId value="CommonCodesVS"/></resource><resource><extension url="http://hl7.org/fhir/tools/StructureDefinition/resource-information"><valueString value="ValueSet"/></extension><extension url="http://hl7.org/fhir/StructureDefinition/implementationguide-page"><valueUri value="ValueSet-MassTypeValueSetVS.html"/></extension><reference><reference value="ValueSet/MassTypeValueSetVS"/></reference><name value="Mass Type ValueSet"/><description value="Mass type value set."/><exampleBoolean value="false"/><groupingId value="CommonCodesVS"/></resource><resource><extension url="http://hl7.org/fhir/tools/StructureDefinition/resource-information"><valueString value="ValueSet"/></extension><extension url="http://hl7.org/fhir/StructureDefinition/implementationguide-page"><valueUri value="ValueSet-MGAbnormalityAsymmetriesTypeVS.html"/></extension><reference><reference value="ValueSet/MGAbnormalityAsymmetriesTypeVS"/></reference><name value="Mammography AsymmetryAbnormalities ValueSet"/><description value="Mammography asymmetry abnormality types value set."/><exampleBoolean value="false"/><groupingId value="MGCodesVS"/></resource><resource><extension url="http://hl7.org/fhir/tools/StructureDefinition/resource-information"><valueString value="ValueSet"/></extension><extension url="http://hl7.org/fhir/StructureDefinition/implementationguide-page"><valueUri value="ValueSet-MGAbnormalityDensityTypeVS.html"/></extension><reference><reference value="ValueSet/MGAbnormalityDensityTypeVS"/></reference><name value="Mammography Density Type ValueSet"/><description value="Mammography density abnormality refinement value set."/><exampleBoolean value="false"/><groupingId value="MGCodesVS"/></resource><resource><extension url="http://hl7.org/fhir/tools/StructureDefinition/resource-information"><valueString value="ValueSet"/></extension><extension url="http://hl7.org/fhir/StructureDefinition/implementationguide-page"><valueUri value="ValueSet-MGBreastDensityVS.html"/></extension><reference><reference value="ValueSet/MGBreastDensityVS"/></reference><name value="Mammography Breast Density ValueSet"/><description value="Mammography breast density value set."/><exampleBoolean value="false"/><groupingId value="MGCodesVS"/></resource><resource><extension url="http://hl7.org/fhir/tools/StructureDefinition/resource-information"><valueString value="ValueSet"/></extension><extension url="http://hl7.org/fhir/StructureDefinition/implementationguide-page"><valueUri value="ValueSet-MGDensityVS.html"/></extension><reference><reference value="ValueSet/MGDensityVS"/></reference><name value="Mammography Density ValueSet"/><description value="Mammography density codes value set."/><exampleBoolean value="false"/><groupingId value="MGCodesVS"/></resource><resource><extension url="http://hl7.org/fhir/tools/StructureDefinition/resource-information"><valueString value="ValueSet"/></extension><extension url="http://hl7.org/fhir/StructureDefinition/implementationguide-page"><valueUri value="ValueSet-NotPreviouslySeenVS.html"/></extension><reference><reference value="ValueSet/NotPreviouslySeenVS"/></reference><name value="NotPreviouslySeen ValueSet"/><description value="NotPreviouslySeen value set."/><exampleBoolean value="false"/><groupingId value="CommonCodesVS"/></resource><resource><extension url="http://hl7.org/fhir/tools/StructureDefinition/resource-information"><valueString value="ValueSet"/></extension><extension url="http://hl7.org/fhir/StructureDefinition/implementationguide-page"><valueUri value="ValueSet-ObservedChangesVS.html"/></extension><reference><reference value="ValueSet/ObservedChangesVS"/></reference><name value="Observed Changes ValueSet"/><description value="Observed changes in an abnormality value set."/><exampleBoolean value="false"/><groupingId value="CommonCodesVS"/></resource><resource><extension url="http://hl7.org/fhir/tools/StructureDefinition/resource-information"><valueString value="ValueSet"/></extension><extension url="http://hl7.org/fhir/StructureDefinition/implementationguide-page"><valueUri value="ValueSet-ObservedFeatureVS.html"/></extension><reference><reference value="ValueSet/ObservedFeatureVS"/></reference><name value="Observed Feature ValueSet"/><description value="Observed feature observed during a Breast Radiology exam value set"/><exampleBoolean value="false"/><groupingId value="CommonCodesVS"/></resource><resource><extension url="http://hl7.org/fhir/tools/StructureDefinition/resource-information"><valueString value="ValueSet"/></extension><extension url="http://hl7.org/fhir/StructureDefinition/implementationguide-page"><valueUri value="ValueSet-OrientationVS.html"/></extension><reference><reference value="ValueSet/OrientationVS"/></reference><name value="Orientation ValueSet"/><description value="Orientation ValueSet"/><exampleBoolean value="false"/><groupingId value="CommonCodesVS"/></resource><resource><extension url="http://hl7.org/fhir/tools/StructureDefinition/resource-information"><valueString value="ValueSet"/></extension><extension url="http://hl7.org/fhir/StructureDefinition/implementationguide-page"><valueUri value="ValueSet-RecommendationsVS.html"/></extension><reference><reference value="ValueSet/RecommendationsVS"/></reference><name value="Recommendations ValueSet"/><description value="Recommendations value set."/><exampleBoolean value="false"/><groupingId value="CommonCodesVS"/></resource><resource><extension url="http://hl7.org/fhir/tools/StructureDefinition/resource-information"><valueString value="ValueSet"/></extension><extension url="http://hl7.org/fhir/StructureDefinition/implementationguide-page"><valueUri value="ValueSet-ShapeVS.html"/></extension><reference><reference value="ValueSet/ShapeVS"/></reference><name value="Shape ValueSet"/><description value="Shape value set."/><exampleBoolean value="false"/><groupingId value="CommonCodesVS"/></resource><resource><extension url="http://hl7.org/fhir/tools/StructureDefinition/resource-information"><valueString value="ValueSet"/></extension><extension url="http://hl7.org/fhir/StructureDefinition/implementationguide-page"><valueUri value="ValueSet-UnitsOfLengthVS.html"/></extension><reference><reference value="ValueSet/UnitsOfLengthVS"/></reference><name value="UnitsOfLength ValueSet"/><description value="UnitsOfLength value set."/><exampleBoolean value="false"/><groupingId value="CommonCodesVS"/></resource><resource><extension url="http://hl7.org/fhir/tools/StructureDefinition/resource-information"><valueString value="StructureDefinition:resource"/></extension><extension url="http://hl7.org/fhir/StructureDefinition/implementationguide-page"><valueUri value="StructureDefinition-BreastRadComposition.html"/></extension><reference><reference value="StructureDefinition/BreastRadComposition"/></reference><name value="Breast Radiology Composition"/><description value="Breast Radiology Composition"/><exampleBoolean value="false"/><groupingId value="BaseResources"/></resource><resource><extension url="http://hl7.org/fhir/tools/StructureDefinition/resource-information"><valueString value="StructureDefinition:resource"/></extension><extension url="http://hl7.org/fhir/StructureDefinition/implementationguide-page"><valueUri value="StructureDefinition-ServiceRecommendation.html"/></extension><reference><reference value="StructureDefinition/ServiceRecommendation"/></reference><name value="Service Recommendation"/><description value="Service Recommendation"/><exampleBoolean value="false"/><groupingId value="BaseResources"/></resource><resource><extension url="http://hl7.org/fhir/tools/StructureDefinition/resource-information"><valueString value="StructureDefinition:resource"/></extension><extension url="http://hl7.org/fhir/StructureDefinition/implementationguide-page"><valueUri value="StructureDefinition-BreastRadReport.html"/></extension><reference><reference value="StructureDefinition/BreastRadReport"/></reference><name value="Breast Radiology Report"/><description value="Breast Radiology Diagnostic Report"/><exampleBoolean value="false"/><groupingId value="BaseResources"/></resource><resource><extension url="http://hl7.org/fhir/tools/StructureDefinition/resource-information"><valueString value="StructureDefinition:resource"/></extension><extension url="http://hl7.org/fhir/StructureDefinition/implementationguide-page"><valueUri value="StructureDefinition-SectionFindingsLeftBreast.html"/></extension><reference><reference value="StructureDefinition/SectionFindingsLeftBreast"/></reference><name value="Findings Left Breast"/><description value="Findings Left Breast Section"/><exampleBoolean value="false"/><groupingId value="BaseResources"/></resource><resource><extension url="http://hl7.org/fhir/tools/StructureDefinition/resource-information"><valueString value="StructureDefinition:resource"/></extension><extension url="http://hl7.org/fhir/StructureDefinition/implementationguide-page"><valueUri value="StructureDefinition-SectionFindingsRightBreast.html"/></extension><reference><reference value="StructureDefinition/SectionFindingsRightBreast"/></reference><name value="Findings Right Breast"/><description value="Findings Right Breast Section"/><exampleBoolean value="false"/><groupingId value="BaseResources"/></resource><resource><extension url="http://hl7.org/fhir/tools/StructureDefinition/resource-information"><valueString value="StructureDefinition:resource"/></extension><extension url="http://hl7.org/fhir/StructureDefinition/implementationguide-page"><valueUri value="StructureDefinition-AbnormalityCyst.html"/></extension><reference><reference value="StructureDefinition/AbnormalityCyst"/></reference><name value="Cyst"/><description value="Cyst Observation"/><exampleBoolean value="false"/><groupingId value="CommonResources"/></resource><resource><extension url="http://hl7.org/fhir/tools/StructureDefinition/resource-information"><valueString value="StructureDefinition:resource"/></extension><extension url="http://hl7.org/fhir/StructureDefinition/implementationguide-page"><valueUri value="StructureDefinition-AbnormalityDuct.html"/></extension><reference><reference value="StructureDefinition/AbnormalityDuct"/></reference><name value="Duct"/><description value="Duct Observation"/><exampleBoolean value="false"/><groupingId value="CommonResources"/></resource><resource><extension url="http://hl7.org/fhir/tools/StructureDefinition/resource-information"><valueString value="StructureDefinition:resource"/></extension><extension url="http://hl7.org/fhir/StructureDefinition/implementationguide-page"><valueUri value="StructureDefinition-AbnormalityFibroadenoma.html"/></extension><reference><reference value="StructureDefinition/AbnormalityFibroadenoma"/></reference><name value="Fibroadenoma"/><description value="Fibroadenoma Observation"/><exampleBoolean value="false"/><groupingId value="CommonResources"/></resource><resource><extension url="http://hl7.org/fhir/tools/StructureDefinition/resource-information"><valueString value="StructureDefinition:resource"/></extension><extension url="http://hl7.org/fhir/StructureDefinition/implementationguide-page"><valueUri value="StructureDefinition-AbnormalityForeignObject.html"/></extension><reference><reference value="StructureDefinition/AbnormalityForeignObject"/></reference><name value="Foreign Object"/><description value="Foreign Object Observation"/><exampleBoolean value="false"/><groupingId value="CommonResources"/></resource><resource><extension url="http://hl7.org/fhir/tools/StructureDefinition/resource-information"><valueString value="StructureDefinition:resource"/></extension><extension url="http://hl7.org/fhir/StructureDefinition/implementationguide-page"><valueUri value="StructureDefinition-AbnormalityLymphNode.html"/></extension><reference><reference value="StructureDefinition/AbnormalityLymphNode"/></reference><name value="LymphNode"/><description value="LymphNode Observation"/><exampleBoolean value="false"/><groupingId value="CommonResources"/></resource><resource><extension url="http://hl7.org/fhir/tools/StructureDefinition/resource-information"><valueString value="StructureDefinition:resource"/></extension><extension url="http://hl7.org/fhir/StructureDefinition/implementationguide-page"><valueUri value="StructureDefinition-AssociatedFeatures.html"/></extension><reference><reference value="StructureDefinition/AssociatedFeatures"/></reference><name value="Associated Features"/><description value="Associated Features Observation"/><exampleBoolean value="false"/><groupingId value="CommonResources"/></resource><resource><extension url="http://hl7.org/fhir/tools/StructureDefinition/resource-information"><valueString value="StructureDefinition:resource"/></extension><extension url="http://hl7.org/fhir/StructureDefinition/implementationguide-page"><valueUri value="StructureDefinition-ObservedFeature.html"/></extension><reference><reference value="StructureDefinition/ObservedFeature"/></reference><name value="Observed Feature"/><description value="Observed Feature Observation"/><exampleBoolean value="false"/><groupingId value="CommonResources"/></resource><resource><extension url="http://hl7.org/fhir/tools/StructureDefinition/resource-information"><valueString value="StructureDefinition:resource"/></extension><extension url="http://hl7.org/fhir/StructureDefinition/implementationguide-page"><valueUri value="StructureDefinition-ConsistentWith.html"/></extension><reference><reference value="StructureDefinition/ConsistentWith"/></reference><name value="Consistent With"/><description value="'Consistent With' Observation"/><exampleBoolean value="false"/><groupingId value="CommonResources"/></resource><resource><extension url="http://hl7.org/fhir/tools/StructureDefinition/resource-information"><valueString value="StructureDefinition:resource"/></extension><extension url="http://hl7.org/fhir/StructureDefinition/implementationguide-page"><valueUri value="StructureDefinition-AbnormalityMass.html"/></extension><reference><reference value="StructureDefinition/AbnormalityMass"/></reference><name value="Mass"/><description value="Mass Observation"/><exampleBoolean value="false"/><groupingId value="CommonResources"/></resource><resource><extension url="http://hl7.org/fhir/tools/StructureDefinition/resource-information"><valueString value="StructureDefinition:extension"/></extension><extension url="http://hl7.org/fhir/StructureDefinition/implementationguide-page"><valueUri value="StructureDefinition-BodyDistanceFromExtension.html"/></extension><reference><reference value="StructureDefinition/BodyDistanceFromExtension"/></reference><name value="Body Distance From Extension"/><description value="Body Distance From extension"/><exampleBoolean value="false"/><groupingId value="ExtensionResources"/></resource><resource><extension url="http://hl7.org/fhir/tools/StructureDefinition/resource-information"><valueString value="StructureDefinition:extension"/></extension><extension url="http://hl7.org/fhir/StructureDefinition/implementationguide-page"><valueUri value="StructureDefinition-BreastBodyLocationExtension.html"/></extension><reference><reference value="StructureDefinition/BreastBodyLocationExtension"/></reference><name value="Breast Body Location Extension"/><description value="Breast Body Location extension"/><exampleBoolean value="false"/><groupingId value="ExtensionResources"/></resource><resource><extension url="http://hl7.org/fhir/tools/StructureDefinition/resource-information"><valueString value="StructureDefinition:extension"/></extension><extension url="http://hl7.org/fhir/StructureDefinition/implementationguide-page"><valueUri value="StructureDefinition-TumorSatelliteExtension.html"/></extension><reference><reference value="StructureDefinition/TumorSatelliteExtension"/></reference><name value="Tumor Satellite Extension"/><description value="Tumor Satellite Extension"/><exampleBoolean value="false"/><groupingId value="ExtensionResources"/></resource><resource><extension url="http://hl7.org/fhir/tools/StructureDefinition/resource-information"><valueString value="StructureDefinition:resource"/></extension><extension url="http://hl7.org/fhir/StructureDefinition/implementationguide-page"><valueUri value="StructureDefinition-MGFinding.html"/></extension><reference><reference value="StructureDefinition/MGFinding"/></reference><name value="Mammography Finding"/><description value="Mammography Finding"/><exampleBoolean value="false"/><groupingId value="MGResources"/></resource><resource><extension url="http://hl7.org/fhir/tools/StructureDefinition/resource-information"><valueString value="StructureDefinition:resource"/></extension><extension url="http://hl7.org/fhir/StructureDefinition/implementationguide-page"><valueUri value="StructureDefinition-MGAbnormalityArchitecturalDistortion.html"/></extension><reference><reference value="StructureDefinition/MGAbnormalityArchitecturalDistortion"/></reference><name value="Mammography Architectural Distortion"/><description value="Architectural Distortion Observation"/><exampleBoolean value="false"/><groupingId value="MGResources"/></resource><resource><extension url="http://hl7.org/fhir/tools/StructureDefinition/resource-information"><valueString value="StructureDefinition:resource"/></extension><extension url="http://hl7.org/fhir/StructureDefinition/implementationguide-page"><valueUri value="StructureDefinition-MGAbnormalityAsymmetry.html"/></extension><reference><reference value="StructureDefinition/MGAbnormalityAsymmetry"/></reference><name value="Mammography Asymmetry"/><description value="Asymmetry Observation"/><exampleBoolean value="false"/><groupingId value="MGResources"/></resource><resource><extension url="http://hl7.org/fhir/tools/StructureDefinition/resource-information"><valueString value="StructureDefinition:resource"/></extension><extension url="http://hl7.org/fhir/StructureDefinition/implementationguide-page"><valueUri value="StructureDefinition-MGAbnormalityDensity.html"/></extension><reference><reference value="StructureDefinition/MGAbnormalityDensity"/></reference><name value="Mammography Density"/><description value="Mammography Density Observation"/><exampleBoolean value="false"/><groupingId value="MGResources"/></resource><resource><extension url="http://hl7.org/fhir/tools/StructureDefinition/resource-information"><valueString value="StructureDefinition:resource"/></extension><extension url="http://hl7.org/fhir/StructureDefinition/implementationguide-page"><valueUri value="StructureDefinition-MGAbnormalityFatNecrosis.html"/></extension><reference><reference value="StructureDefinition/MGAbnormalityFatNecrosis"/></reference><name value="Mammography Fat Necrosis"/><description value="Fat Necrosis Observation"/><exampleBoolean value="false"/><groupingId value="MGResources"/></resource><resource><extension url="http://hl7.org/fhir/tools/StructureDefinition/resource-information"><valueString value="StructureDefinition:resource"/></extension><extension url="http://hl7.org/fhir/StructureDefinition/implementationguide-page"><valueUri value="StructureDefinition-MGBreastDensity.html"/></extension><reference><reference value="StructureDefinition/MGBreastDensity"/></reference><name value="Mammography Breast Density"/><description value="Breast Density Observation"/><exampleBoolean value="false"/><groupingId value="MGResources"/></resource><resource><extension url="http://hl7.org/fhir/tools/StructureDefinition/resource-information"><valueString value="StructureDefinition:resource"/></extension><extension url="http://hl7.org/fhir/StructureDefinition/implementationguide-page"><valueUri value="StructureDefinition-MGAbnormalityCalcification.html"/></extension><reference><reference value="StructureDefinition/MGAbnormalityCalcification"/></reference><name value="Mammography Calcification"/><description value="Calcification Observation"/><exampleBoolean value="false"/><groupingId value="MGResources"/></resource><resource><extension url="http://hl7.org/fhir/tools/StructureDefinition/resource-information"><valueString value="StructureDefinition:resource"/></extension><extension url="http://hl7.org/fhir/StructureDefinition/implementationguide-page"><valueUri value="StructureDefinition-MRIFinding.html"/></extension><reference><reference value="StructureDefinition/MRIFinding"/></reference><name value="MRI Finding"/><description value="MRI Finding"/><exampleBoolean value="false"/><groupingId value="MRIResources"/></resource><resource><extension url="http://hl7.org/fhir/tools/StructureDefinition/resource-information"><valueString value="StructureDefinition:resource"/></extension><extension url="http://hl7.org/fhir/StructureDefinition/implementationguide-page"><valueUri value="StructureDefinition-NMFinding.html"/></extension><reference><reference value="StructureDefinition/NMFinding"/></reference><name value="NM Finding"/><description value="NM Finding"/><exampleBoolean value="false"/><groupingId value="NMResources"/></resource><resource><extension url="http://hl7.org/fhir/tools/StructureDefinition/resource-information"><valueString value="StructureDefinition:resource"/></extension><extension url="http://hl7.org/fhir/StructureDefinition/implementationguide-page"><valueUri value="StructureDefinition-USFinding.html"/></extension><reference><reference value="StructureDefinition/USFinding"/></reference><name value="Ultra-Sound Finding"/><description value="Ultra Sound Finding"/><exampleBoolean value="false"/><groupingId value="USResources"/></resource><resource><extension url="http://hl7.org/fhir/tools/StructureDefinition/resource-information"><valueString value="StructureDefinition:resource:abstract"/></extension><extension url="http://hl7.org/fhir/StructureDefinition/implementationguide-page"><valueUri value="StructureDefinition-BiRadFragment.html"/></extension><reference><reference value="StructureDefinition/BiRadFragment"/></reference><name value="BiRad Fragment"/><description value="Fragment 'Fragment that adds 'BiRad code' element to profile.'"/><exampleBoolean value="false"/><groupingId value="Fragments"/></resource><resource><extension url="http://hl7.org/fhir/tools/StructureDefinition/resource-information"><valueString value="StructureDefinition:resource:abstract"/></extension><extension url="http://hl7.org/fhir/StructureDefinition/implementationguide-page"><valueUri value="StructureDefinition-BreastBodyLocationRequiredFragment.html"/></extension><reference><reference value="StructureDefinition/BreastBodyLocationRequiredFragment"/></reference><name value="Breast Body Location (Required) Fragment"/><description value="Fragment 'Required Breast Body Location fragment'"/><exampleBoolean value="false"/><groupingId value="Fragments"/></resource><resource><extension url="http://hl7.org/fhir/tools/StructureDefinition/resource-information"><valueString value="StructureDefinition:resource:abstract"/></extension><extension url="http://hl7.org/fhir/StructureDefinition/implementationguide-page"><valueUri value="StructureDefinition-BreastRadObservationFragment.html"/></extension><reference><reference value="StructureDefinition/BreastRadObservationFragment"/></reference><name value="Observation Fragment"/><description value="Fragment 'Observation base fragment'"/><exampleBoolean value="false"/><groupingId value="Fragments"/></resource><resource><extension url="http://hl7.org/fhir/tools/StructureDefinition/resource-information"><valueString value="StructureDefinition:resource:abstract"/></extension><extension url="http://hl7.org/fhir/StructureDefinition/implementationguide-page"><valueUri value="StructureDefinition-BreastRadObservationNoComponentFragment.html"/></extension><reference><reference value="StructureDefinition/BreastRadObservationNoComponentFragment"/></reference><name value="Observation No Component Fragment"/><description value="Fragment 'Observation NoComponent Fragment.'"/><exampleBoolean value="false"/><groupingId value="Fragments"/></resource><resource><extension url="http://hl7.org/fhir/tools/StructureDefinition/resource-information"><valueString value="StructureDefinition:resource:abstract"/></extension><extension url="http://hl7.org/fhir/StructureDefinition/implementationguide-page"><valueUri value="StructureDefinition-BreastRadObservationNoDeviceFragment.html"/></extension><reference><reference value="StructureDefinition/BreastRadObservationNoDeviceFragment"/></reference><name value="Observation NoDevice Fragment"/><description value="Fragment 'Observations No Device Data fragment.'"/><exampleBoolean value="false"/><groupingId value="Fragments"/></resource><resource><extension url="http://hl7.org/fhir/tools/StructureDefinition/resource-information"><valueString value="StructureDefinition:resource:abstract"/></extension><extension url="http://hl7.org/fhir/StructureDefinition/implementationguide-page"><valueUri value="StructureDefinition-BreastRadObservationNoValueFragment.html"/></extension><reference><reference value="StructureDefinition/BreastRadObservationNoValueFragment"/></reference><name value="Observation NoValue Fragment"/><description value="Fragment 'Observation No Value fragment'"/><exampleBoolean value="false"/><groupingId value="Fragments"/></resource><resource><extension url="http://hl7.org/fhir/tools/StructureDefinition/resource-information"><valueString value="StructureDefinition:resource:abstract"/></extension><extension url="http://hl7.org/fhir/StructureDefinition/implementationguide-page"><valueUri value="StructureDefinition-CategoryFragment.html"/></extension><reference><reference value="StructureDefinition/CategoryFragment"/></reference><name value="Category Fragment"/><description value="Fragment 'Fix Observation.category Fragment'"/><exampleBoolean value="false"/><groupingId value="Fragments"/></resource><resource><extension url="http://hl7.org/fhir/tools/StructureDefinition/resource-information"><valueString value="StructureDefinition:resource:abstract"/></extension><extension url="http://hl7.org/fhir/StructureDefinition/implementationguide-page"><valueUri value="StructureDefinition-CommonComponentsFragment.html"/></extension><reference><reference value="StructureDefinition/CommonComponentsFragment"/></reference><name value="Common Components Fragment"/><description value="Fragment 'Common Components fragment'"/><exampleBoolean value="false"/><groupingId value="Fragments"/></resource><resource><extension url="http://hl7.org/fhir/tools/StructureDefinition/resource-information"><valueString value="StructureDefinition:resource:abstract"/></extension><extension url="http://hl7.org/fhir/StructureDefinition/implementationguide-page"><valueUri value="StructureDefinition-CorrespondsWithFragment.html"/></extension><reference><reference value="StructureDefinition/CorrespondsWithFragment"/></reference><name value="CorrespondsWith Fragment"/><description value="Fragment 'Observation 'Consistent With' Component Fragment'"/><exampleBoolean value="false"/><groupingId value="Fragments"/></resource><resource><extension url="http://hl7.org/fhir/tools/StructureDefinition/resource-information"><valueString value="StructureDefinition:resource:abstract"/></extension><extension url="http://hl7.org/fhir/StructureDefinition/implementationguide-page"><valueUri value="StructureDefinition-FindingBreastFragment.html"/></extension><reference><reference value="StructureDefinition/FindingBreastFragment"/></reference><name value="Finding Breast Fragment"/><description value="Fragment 'Fragment definition for finding section of left or right breast'"/><exampleBoolean value="false"/><groupingId value="Fragments"/></resource><resource><extension url="http://hl7.org/fhir/tools/StructureDefinition/resource-information"><valueString value="StructureDefinition:resource:abstract"/></extension><extension url="http://hl7.org/fhir/StructureDefinition/implementationguide-page"><valueUri value="StructureDefinition-HeaderFragment.html"/></extension><reference><reference value="StructureDefinition/HeaderFragment"/></reference><name value="Header Fragment"/><description value="Fragment 'Common Header Fragment'"/><exampleBoolean value="false"/><groupingId value="Fragments"/></resource><resource><extension url="http://hl7.org/fhir/tools/StructureDefinition/resource-information"><valueString value="StructureDefinition:resource:abstract"/></extension><extension url="http://hl7.org/fhir/StructureDefinition/implementationguide-page"><valueUri value="StructureDefinition-NotPreviouslySeenComponentFragment.html"/></extension><reference><reference value="StructureDefinition/NotPreviouslySeenComponentFragment"/></reference><name value="Not Previously Seen Component Fragment"/><description value="Fragment 'Not Previously Seen component slice fragment'"/><exampleBoolean value="false"/><groupingId value="Fragments"/></resource><resource><extension url="http://hl7.org/fhir/tools/StructureDefinition/resource-information"><valueString value="StructureDefinition:resource:abstract"/></extension><extension url="http://hl7.org/fhir/StructureDefinition/implementationguide-page"><valueUri value="StructureDefinition-ObservationLeafFragment.html"/></extension><reference><reference value="StructureDefinition/ObservationLeafFragment"/></reference><name value="Observation Leaf Fragment"/><description value="Fragment 'Observation Leaf Node Fragment'"/><exampleBoolean value="false"/><groupingId value="Fragments"/></resource><resource><extension url="http://hl7.org/fhir/tools/StructureDefinition/resource-information"><valueString value="StructureDefinition:resource:abstract"/></extension><extension url="http://hl7.org/fhir/StructureDefinition/implementationguide-page"><valueUri value="StructureDefinition-ObservationSectionFragment.html"/></extension><reference><reference value="StructureDefinition/ObservationSectionFragment"/></reference><name value="Observation Section Fragment"/><description value="Fragment 'Observation section fragment'"/><exampleBoolean value="false"/><groupingId value="Fragments"/></resource><resource><extension url="http://hl7.org/fhir/tools/StructureDefinition/resource-information"><valueString value="StructureDefinition:resource:abstract"/></extension><extension url="http://hl7.org/fhir/StructureDefinition/implementationguide-page"><valueUri value="StructureDefinition-ObservedChangesFragment.html"/></extension><reference><reference value="StructureDefinition/ObservedChangesFragment"/></reference><name value="ObservedChanges Fragment"/><description value="Fragment 'Fragment that adds 'Observed Changes' element to profile.'"/><exampleBoolean value="false"/><groupingId value="Fragments"/></resource><resource><extension url="http://hl7.org/fhir/tools/StructureDefinition/resource-information"><valueString value="StructureDefinition:resource:abstract"/></extension><extension url="http://hl7.org/fhir/StructureDefinition/implementationguide-page"><valueUri value="StructureDefinition-ObservedCountFragment.html"/></extension><reference><reference value="StructureDefinition/ObservedCountFragment"/></reference><name value="ObservedCount Fragment"/><description value="Fragment 'Fragment that adds 'Observed Count' element to profile.'"/><exampleBoolean value="false"/><groupingId value="Fragments"/></resource><resource><extension url="http://hl7.org/fhir/tools/StructureDefinition/resource-information"><valueString value="StructureDefinition:resource:abstract"/></extension><extension url="http://hl7.org/fhir/StructureDefinition/implementationguide-page"><valueUri value="StructureDefinition-ObservedDistributionFragment.html"/></extension><reference><reference value="StructureDefinition/ObservedDistributionFragment"/></reference><name value="ObservedDistribution Fragment"/><description value="Fragment 'Fragment that adds 'Observed Distribution' components to Observation.'"/><exampleBoolean value="false"/><groupingId value="Fragments"/></resource><resource><extension url="http://hl7.org/fhir/tools/StructureDefinition/resource-information"><valueString value="StructureDefinition:resource:abstract"/></extension><extension url="http://hl7.org/fhir/StructureDefinition/implementationguide-page"><valueUri value="StructureDefinition-ObservedSizeFragment.html"/></extension><reference><reference value="StructureDefinition/ObservedSizeFragment"/></reference><name value="ObservedSize Fragment"/><description value="Fragment 'Fragment that adds 'Observed Size' components to Observation.'"/><exampleBoolean value="false"/><groupingId value="Fragments"/></resource><resource><extension url="http://hl7.org/fhir/tools/StructureDefinition/resource-information"><valueString value="StructureDefinition:resource:abstract"/></extension><extension url="http://hl7.org/fhir/StructureDefinition/implementationguide-page"><valueUri value="StructureDefinition-ShapeComponentsFragment.html"/></extension><reference><reference value="StructureDefinition/ShapeComponentsFragment"/></reference><name value="Shape Components Fragment"/><description value="Fragment 'Shape component slice fragment'"/><exampleBoolean value="false"/><groupingId value="Fragments"/></resource><resource><extension url="http://hl7.org/fhir/tools/StructureDefinition/resource-information"><valueString value="StructureDefinition:resource:abstract"/></extension><extension url="http://hl7.org/fhir/StructureDefinition/implementationguide-page"><valueUri value="StructureDefinition-TumorSatelliteFragment.html"/></extension><reference><reference value="StructureDefinition/TumorSatelliteFragment"/></reference><name value="Tumor Satellite Fragment"/><description value="Fragment 'Tumor Satellite fragment'"/><exampleBoolean value="false"/><groupingId value="Fragments"/></resource><resource><extension url="http://hl7.org/fhir/tools/StructureDefinition/resource-information"><valueString value="CodeSystem"/></extension><extension url="http://hl7.org/fhir/StructureDefinition/implementationguide-page"><valueUri value="CodeSystem-MammoCalcificationDistributionCS.html"/></extension><reference><reference value="CodeSystem/MammoCalcificationDistributionCS"/></reference><name value="Mammography Calcification Distribution CodeSystem"/><description value="Mammography calcification distribution code system."/><groupingId value="_term_codesystem"/></resource><resource><extension url="http://hl7.org/fhir/tools/StructureDefinition/resource-information"><valueString value="CodeSystem"/></extension><extension url="http://hl7.org/fhir/StructureDefinition/implementationguide-page"><valueUri value="CodeSystem-ObservedDistributionCS.html"/></extension><reference><reference value="CodeSystem/ObservedDistributionCS"/></reference><name value="Observed Distribution CodeSystem"/><description value="Observed Distribution in an abnormality code system."/><groupingId value="_term_codesystem"/></resource><resource><extension url="http://hl7.org/fhir/tools/StructureDefinition/resource-information"><valueString value="StructureDefinition:resource"/></extension><extension url="http://hl7.org/fhir/StructureDefinition/implementationguide-page"><valueUri value="StructureDefinition-ObservedItemGroup.html"/></extension><reference><reference value="StructureDefinition/ObservedItemGroup"/></reference><name value="Observed ItemGroup"/><description value="&lt;b&gt;Observation of a size or size range in 1, 2, or 3 dimensions.&lt;/b&gt;&#xA;&#xA;Observation of a one or more items and the size and grouping of the item(s)&#xA;&#xA;The size can be one, two, or three dimensional.&#xA; The axes can be oriented to certain landmarks, or ordered by size.&#xA; Each dimention can be a quantity (i.e. 5 cm), or a range (1 cm to 5 cm).&#xA; If the lower bound of the range is set but not the upper bound, then it means {lower bound} cm or more.&#xA; If the upper bound of the range is set but not the lower bound, then it means {upper bound} cm or less."/><groupingId value="_str_profile"/></resource><resource><extension url="http://hl7.org/fhir/tools/StructureDefinition/resource-information"><valueString value="ValueSet"/></extension><extension url="http://hl7.org/fhir/StructureDefinition/implementationguide-page"><valueUri value="ValueSet-ItemGroupComponentCodesVS.html"/></extension><reference><reference value="ValueSet/ItemGroupComponentCodesVS"/></reference><name value="Item Group Component Codes ValueSet"/><description value="Item Group Component Codes value set."/><groupingId value="_term_valueset"/></resource><resource><extension url="http://hl7.org/fhir/tools/StructureDefinition/resource-information"><valueString value="ValueSet"/></extension><extension url="http://hl7.org/fhir/StructureDefinition/implementationguide-page"><valueUri value="ValueSet-MammoCalcificationDistributionVS.html"/></extension><reference><reference value="ValueSet/MammoCalcificationDistributionVS"/></reference><name value="Mammography Calcification Distribution ValueSet"/><description value="Mammography calcification distribution value set."/><groupingId value="_term_valueset"/></resource><resource><extension url="http://hl7.org/fhir/tools/StructureDefinition/resource-information"><valueString value="ValueSet"/></extension><extension url="http://hl7.org/fhir/StructureDefinition/implementationguide-page"><valueUri value="ValueSet-ObservedDistributionVS.html"/></extension><reference><reference value="ValueSet/ObservedDistributionVS"/></reference><name value="Observed Distribution ValueSet"/><description value="Observed Distribution of an abnormality value set."/><groupingId value="_term_valueset"/></resource><page><nameUrl value="toc.html"/><title value="Table of Contents"/><generation value="html"/><page><nameUrl value="index.html"/><title value="Breast Radiology Reporting - 1st STU ballot"/><generation value="html"/></page><page><nameUrl value="background.html"/><title value="Background"/><generation value="html"/></page><page><nameUrl value="spec.html"/><title value="Overview"/><generation value="html"/></page><page><nameUrl value="mgfinding.html"/><title value="Mammography Finding"/><generation value="html"/></page><page><nameUrl value="usfinding.html"/><title value="Ultra-Sound Finding"/><generation value="html"/></page><page><nameUrl value="mrifinding.html"/><title value="MRI Finding"/><generation value="html"/></page><page><nameUrl value="nmfinding.html"/><title value="Nuclear Medicine Finding"/><generation value="html"/></page><page><nameUrl value="fragments.html"/><title value="Resource Fragments"/><generation value="html"/></page><page><nameUrl value="downloads.html"/><title value="Useful Downloads"/><generation value="html"/></page><page><nameUrl value="changes.html"/><title value="IG Change History"/><generation value="html"/></page></page><parameter><code value="copyrightyear"/><value value="2019+"/></parameter><parameter><code value="releaselabel"/><value value="CI Build"/></parameter><parameter><code value="autoload-resources"/><value value="true"/></parameter><parameter><code value="path-resource"/><value value="input/capabilities"/></parameter><parameter><code value="path-resource"/><value value="input/examples"/></parameter><parameter><code value="path-resource"/><value value="input/extensions"/></parameter><parameter><code value="path-resource"/><value value="input/models"/></parameter><parameter><code value="path-resource"/><value value="input/operations"/></parameter><parameter><code value="path-resource"/><value value="input/profiles"/></parameter><parameter><code value="path-resource"/><value value="input/resources"/></parameter><parameter><code value="path-resource"/><value value="input/vocabulary"/></parameter><parameter><code value="path-pages"/><value value="template/config"/></parameter><parameter><code value="path-pages"/><value value="input/images"/></parameter><parameter><code value="path-qa"/><value value="temp/qa"/></parameter><parameter><code value="path-temp"/><value value="temp/pages"/></parameter><parameter><code value="path-output"/><value value="output"/></parameter><parameter><code value="path-tx-cache"/><value value="input-cache/txcache"/></parameter><parameter><code value="path-suppressed-warnings"/><value value="input/ignoreWarnings.txt"/></parameter><parameter><code value="template-html"/><value value="template-page.html"/></parameter><parameter><code value="template-md"/><value value="template-page-md.html"/></parameter><parameter><code value="apply-contact"/><value value="true"/></parameter><parameter><code value="apply-context"/><value value="true"/></parameter><parameter><code value="apply-copyright"/><value value="true"/></parameter><parameter><code value="apply-jurisdiction"/><value value="true"/></parameter><parameter><code value="apply-license"/><value value="true"/></parameter><parameter><code value="apply-publisher"/><value value="true"/></parameter><parameter><code value="apply-version"/><value value="true"/></parameter><parameter><code value="active-tables"/><value value="true"/></parameter></definition></ImplementationGuide>