{
  "resourceType": "StructureDefinition",
  "id": "obf-Deceased-model",
  "text": {
    "status": "generated",
    "div": "<div xmlns=\"http://www.w3.org/1999/xhtml\">\n  <p><b>Deceased Logical Model</b></p>\n  <p>An indication that the person is no longer living, given by a date of death, or boolean value. The latter, when true, indicates the person is deceased.</p>\n</div>"
  },
  "url": "http://build.fhir.org/ig/HL7/fhir-breast-radiology-ig//fhir/StructureDefinition/obf-Deceased-model",
  "identifier": [
    {
      "system": "http://build.fhir.org/ig/HL7/fhir-breast-radiology-ig",
      "value": "obf.Deceased"
    }
  ],
  "name": "Deceased",
  "title": "obf-Deceased",
  "status": "draft",
  "date": "2019-07-19",
  "publisher": "Hl7",
  "contact": [
    {
      "telecom": [
        {
          "system": "url",
          "value": "http://BreastRadReport.com"
        }
      ]
    }
  ],
  "description": "An indication that the person is no longer living, given by a date of death, or boolean value. The latter, when true, indicates the person is deceased.",
  "kind": "logical",
  "abstract": false,
  "type": "obf-Deceased-model",
  "baseDefinition": "http://hl7.org/fhir/StructureDefinition/Element",
  "derivation": "specialization",
  "snapshot": {
    "element": [
      {
        "id": "obf-Deceased-model",
        "path": "obf-Deceased-model",
        "definition": "An indication that the person is no longer living, given by a date of death, or boolean value. The latter, when true, indicates the person is deceased.",
        "min": 0,
        "max": "*",
        "base": {
          "path": "obf-Deceased-model",
          "min": 0,
          "max": "*"
        },
        "mustSupport": false,
        "isModifier": false,
        "isSummary": false
      },
      {
        "id": "obf-Deceased-model.value[x]",
        "path": "obf-Deceased-model.value[x]",
        "short": "Boolean or dateTime representing an indication that the person is no longer living, given by a date of death, or boolean value. The latter, when true, indicates the person is deceased.",
        "definition": "Boolean or dateTime representing an indication that the person is no longer living, given by a date of death, or boolean value. The latter, when true, indicates the person is deceased.",
        "min": 1,
        "max": "1",
        "base": {
          "path": "obf-Deceased-model.value[x]",
          "min": 1,
          "max": "1"
        },
        "type": [
          {
            "code": "boolean"
          },
          {
            "code": "dateTime"
          }
        ],
        "mustSupport": false,
        "isModifier": false,
        "isSummary": false
      }
    ]
  },
  "differential": {
    "element": [
      {
        "id": "obf-Deceased-model",
        "path": "obf-Deceased-model",
        "definition": "An indication that the person is no longer living, given by a date of death, or boolean value. The latter, when true, indicates the person is deceased.",
        "min": 0,
        "max": "*",
        "base": {
          "path": "obf-Deceased-model",
          "min": 0,
          "max": "*"
        },
        "mustSupport": false,
        "isModifier": false,
        "isSummary": false
      },
      {
        "id": "obf-Deceased-model.value[x]",
        "path": "obf-Deceased-model.value[x]",
        "short": "Boolean or dateTime representing an indication that the person is no longer living, given by a date of death, or boolean value. The latter, when true, indicates the person is deceased.",
        "definition": "Boolean or dateTime representing an indication that the person is no longer living, given by a date of death, or boolean value. The latter, when true, indicates the person is deceased.",
        "min": 1,
        "max": "1",
        "base": {
          "path": "obf-Deceased-model.value[x]",
          "min": 1,
          "max": "1"
        },
        "type": [
          {
            "code": "boolean"
          },
          {
            "code": "dateTime"
          }
        ],
        "mustSupport": false,
        "isModifier": false,
        "isSummary": false
      }
    ]
  }
}