{
  "resourceType": "StructureDefinition",
  "id": "obf-CourseOfTherapyType-model",
  "text": {
    "status": "generated",
    "div": "<div xmlns=\"http://www.w3.org/1999/xhtml\">\n  <p><b>CourseOfTherapyType Logical Model</b></p>\n  <p>The description of the overall pattern of the administration of the medication to the patient.</p>\n</div>"
  },
  "url": "http://build.fhir.org/ig/HL7/fhir-breast-radiology-ig//fhir/StructureDefinition/obf-CourseOfTherapyType-model",
  "identifier": [
    {
      "system": "http://build.fhir.org/ig/HL7/fhir-breast-radiology-ig",
      "value": "obf.CourseOfTherapyType"
    }
  ],
  "name": "CourseOfTherapyType",
  "title": "obf-CourseOfTherapyType",
  "status": "draft",
  "date": "2019-07-19",
  "publisher": "Hl7",
  "contact": [
    {
      "telecom": [
        {
          "system": "url",
          "value": "http://BreastRadReport.com"
        }
      ]
    }
  ],
  "description": "The description of the overall pattern of the administration of the medication to the patient.",
  "kind": "logical",
  "abstract": false,
  "type": "obf-CourseOfTherapyType-model",
  "baseDefinition": "http://hl7.org/fhir/StructureDefinition/Element",
  "derivation": "specialization",
  "snapshot": {
    "element": [
      {
        "id": "obf-CourseOfTherapyType-model",
        "path": "obf-CourseOfTherapyType-model",
        "definition": "The description of the overall pattern of the administration of the medication to the patient.",
        "min": 0,
        "max": "*",
        "base": {
          "path": "obf-CourseOfTherapyType-model",
          "min": 0,
          "max": "*"
        },
        "mustSupport": false,
        "isModifier": false,
        "isSummary": false
      },
      {
        "id": "obf-CourseOfTherapyType-model.value",
        "path": "obf-CourseOfTherapyType-model.value",
        "short": "Concept representing the description of the overall pattern of the administration of the medication to the patient.",
        "definition": "Concept representing the description of the overall pattern of the administration of the medication to the patient.",
        "min": 1,
        "max": "1",
        "base": {
          "path": "obf-CourseOfTherapyType-model.value",
          "min": 1,
          "max": "1"
        },
        "type": [
          {
            "code": "Coding"
          }
        ],
        "mustSupport": false,
        "isModifier": false,
        "isSummary": false
      }
    ]
  },
  "differential": {
    "element": [
      {
        "id": "obf-CourseOfTherapyType-model",
        "path": "obf-CourseOfTherapyType-model",
        "definition": "The description of the overall pattern of the administration of the medication to the patient.",
        "min": 0,
        "max": "*",
        "base": {
          "path": "obf-CourseOfTherapyType-model",
          "min": 0,
          "max": "*"
        },
        "mustSupport": false,
        "isModifier": false,
        "isSummary": false
      },
      {
        "id": "obf-CourseOfTherapyType-model.value",
        "path": "obf-CourseOfTherapyType-model.value",
        "short": "Concept representing the description of the overall pattern of the administration of the medication to the patient.",
        "definition": "Concept representing the description of the overall pattern of the administration of the medication to the patient.",
        "min": 1,
        "max": "1",
        "base": {
          "path": "obf-CourseOfTherapyType-model.value",
          "min": 1,
          "max": "1"
        },
        "type": [
          {
            "code": "Coding"
          }
        ],
        "mustSupport": false,
        "isModifier": false,
        "isSummary": false
      }
    ]
  }
}