{
  "resourceType": "StructureDefinition",
  "id": "obf-datatype-TextMarkdown-model",
  "text": {
    "status": "generated",
    "div": "<div xmlns=\"http://www.w3.org/1999/xhtml\">\n  <p><b>TextMarkdown Logical Model</b></p>\n  <p>A string that may contain markdown syntax for optional processing by a markdown presentation engine, in the GFM extension of CommonMark format.</p>\n</div>"
  },
  "url": "http://hl7.org/fhir/us/breast-radiology/fhir/StructureDefinition/obf-datatype-TextMarkdown-model",
  "identifier": [
    {
      "system": "http://hl7.org/fhir/us/breast-radiology",
      "value": "obf.datatype.TextMarkdown"
    }
  ],
  "name": "TextMarkdown",
  "title": "obf-datatype-TextMarkdown",
  "status": "draft",
  "date": "2019-07-30",
  "publisher": "Hl7",
  "contact": [
    {
      "telecom": [
        {
          "system": "url",
          "value": "http://BreastRadReport.com"
        }
      ]
    }
  ],
  "description": "A string that may contain markdown syntax for optional processing by a markdown presentation engine, in the GFM extension of CommonMark format.",
  "kind": "logical",
  "abstract": false,
  "type": "obf-datatype-TextMarkdown-model",
  "baseDefinition": "http://hl7.org/fhir/StructureDefinition/Element",
  "derivation": "specialization",
  "snapshot": {
    "element": [
      {
        "id": "obf-datatype-TextMarkdown-model",
        "path": "obf-datatype-TextMarkdown-model",
        "definition": "A string that may contain markdown syntax for optional processing by a markdown presentation engine, in the GFM extension of CommonMark format.",
        "min": 0,
        "max": "*",
        "base": {
          "path": "obf-datatype-TextMarkdown-model",
          "min": 0,
          "max": "*"
        },
        "mustSupport": false,
        "isModifier": false,
        "isSummary": false
      },
      {
        "id": "obf-datatype-TextMarkdown-model.value",
        "path": "obf-datatype-TextMarkdown-model.value",
        "short": "Markdown representing a string that may contain markdown syntax for optional processing by a markdown presentation engine, in the GFM extension of CommonMark format.",
        "definition": "Markdown representing a string that may contain markdown syntax for optional processing by a markdown presentation engine, in the GFM extension of CommonMark format.",
        "min": 1,
        "max": "1",
        "base": {
          "path": "obf-datatype-TextMarkdown-model.value",
          "min": 1,
          "max": "1"
        },
        "type": [
          {
            "code": "markdown"
          }
        ],
        "mustSupport": false,
        "isModifier": false,
        "isSummary": false
      }
    ]
  },
  "differential": {
    "element": [
      {
        "id": "obf-datatype-TextMarkdown-model",
        "path": "obf-datatype-TextMarkdown-model",
        "definition": "A string that may contain markdown syntax for optional processing by a markdown presentation engine, in the GFM extension of CommonMark format.",
        "min": 0,
        "max": "*",
        "base": {
          "path": "obf-datatype-TextMarkdown-model",
          "min": 0,
          "max": "*"
        },
        "mustSupport": false,
        "isModifier": false,
        "isSummary": false
      },
      {
        "id": "obf-datatype-TextMarkdown-model.value",
        "path": "obf-datatype-TextMarkdown-model.value",
        "short": "Markdown representing a string that may contain markdown syntax for optional processing by a markdown presentation engine, in the GFM extension of CommonMark format.",
        "definition": "Markdown representing a string that may contain markdown syntax for optional processing by a markdown presentation engine, in the GFM extension of CommonMark format.",
        "min": 1,
        "max": "1",
        "base": {
          "path": "obf-datatype-TextMarkdown-model.value",
          "min": 1,
          "max": "1"
        },
        "type": [
          {
            "code": "markdown"
          }
        ],
        "mustSupport": false,
        "isModifier": false,
        "isSummary": false
      }
    ]
  }
}