{
  "resourceType": "StructureDefinition",
  "id": "shr-core-RepeatBounds-model",
  "text": {
    "status": "generated",
    "div": "<div xmlns=\"http://www.w3.org/1999/xhtml\">\n  <p><b>RepeatBounds Logical Model</b></p>\n  <p>Either a duration for the length of the timing schedule, a range of possible length, or outer bounds for start and/or end limits of the timing schedule.</p>\n</div>"
  },
  "url": "http://build.fhir.org/ig/HL7/fhir-breast-radiology-ig//fhir/StructureDefinition/shr-core-RepeatBounds-model",
  "identifier": [
    {
      "system": "http://build.fhir.org/ig/HL7/fhir-breast-radiology-ig",
      "value": "shr.core.RepeatBounds"
    }
  ],
  "name": "RepeatBounds",
  "title": "shr-core-RepeatBounds",
  "status": "draft",
  "date": "2019-07-26",
  "publisher": "Hl7",
  "contact": [
    {
      "telecom": [
        {
          "system": "url",
          "value": "http://BreastRadReport.com"
        }
      ]
    }
  ],
  "description": "Either a duration for the length of the timing schedule, a range of possible length, or outer bounds for start and/or end limits of the timing schedule.",
  "kind": "logical",
  "abstract": false,
  "type": "shr-core-RepeatBounds-model",
  "baseDefinition": "http://hl7.org/fhir/StructureDefinition/Element",
  "derivation": "specialization",
  "snapshot": {
    "element": [
      {
        "id": "shr-core-RepeatBounds-model",
        "path": "shr-core-RepeatBounds-model",
        "definition": "Either a duration for the length of the timing schedule, a range of possible length, or outer bounds for start and/or end limits of the timing schedule.",
        "min": 0,
        "max": "*",
        "base": {
          "path": "shr-core-RepeatBounds-model",
          "min": 0,
          "max": "*"
        },
        "mustSupport": false,
        "isModifier": false,
        "isSummary": false
      },
      {
        "id": "shr-core-RepeatBounds-model.value[x]",
        "path": "shr-core-RepeatBounds-model.value[x]",
        "short": "Choice of types representing either a duration for the length of the timing schedule, a range of possible length, or outer bounds for start and/or end limits of the timing schedule.",
        "definition": "Choice of types representing either a duration for the length of the timing schedule, a range of possible length, or outer bounds for start and/or end limits of the timing schedule.",
        "min": 1,
        "max": "1",
        "base": {
          "path": "shr-core-RepeatBounds-model.value[x]",
          "min": 1,
          "max": "1"
        },
        "type": [
          {
            "code": "http://build.fhir.org/ig/HL7/fhir-breast-radiology-ig//fhir/StructureDefinition/shr-core-Duration-model"
          },
          {
            "code": "http://build.fhir.org/ig/HL7/fhir-breast-radiology-ig//fhir/StructureDefinition/shr-core-Range-model"
          },
          {
            "code": "http://build.fhir.org/ig/HL7/fhir-breast-radiology-ig//fhir/StructureDefinition/shr-core-TimePeriod-model"
          }
        ],
        "mustSupport": false,
        "isModifier": false,
        "isSummary": false
      }
    ]
  },
  "differential": {
    "element": [
      {
        "id": "shr-core-RepeatBounds-model",
        "path": "shr-core-RepeatBounds-model",
        "definition": "Either a duration for the length of the timing schedule, a range of possible length, or outer bounds for start and/or end limits of the timing schedule.",
        "min": 0,
        "max": "*",
        "base": {
          "path": "shr-core-RepeatBounds-model",
          "min": 0,
          "max": "*"
        },
        "mustSupport": false,
        "isModifier": false,
        "isSummary": false
      },
      {
        "id": "shr-core-RepeatBounds-model.value[x]",
        "path": "shr-core-RepeatBounds-model.value[x]",
        "short": "Choice of types representing either a duration for the length of the timing schedule, a range of possible length, or outer bounds for start and/or end limits of the timing schedule.",
        "definition": "Choice of types representing either a duration for the length of the timing schedule, a range of possible length, or outer bounds for start and/or end limits of the timing schedule.",
        "min": 1,
        "max": "1",
        "base": {
          "path": "shr-core-RepeatBounds-model.value[x]",
          "min": 1,
          "max": "1"
        },
        "type": [
          {
            "code": "http://build.fhir.org/ig/HL7/fhir-breast-radiology-ig//fhir/StructureDefinition/shr-core-Duration-model"
          },
          {
            "code": "http://build.fhir.org/ig/HL7/fhir-breast-radiology-ig//fhir/StructureDefinition/shr-core-Range-model"
          },
          {
            "code": "http://build.fhir.org/ig/HL7/fhir-breast-radiology-ig//fhir/StructureDefinition/shr-core-TimePeriod-model"
          }
        ],
        "mustSupport": false,
        "isModifier": false,
        "isSummary": false
      }
    ]
  }
}